Project_ALU.srcs/sources_1/new/ALU_8bit.v
`timescale 1ns / 1ps
//////////////////////////////////////////////////////////////////////////////////
// Company: 
// Engineer: 
// 
// Create Date: 02.06.2026 12:51:29
// Design Name: 
// Module Name: ALU_8bit
// Project Name: 
// Target Devices: 
// Tool Versions: 
// Description: 
// 
// Dependencies: 
// 
// Revision:
// Revision 0.01 - File Created
// Additional Comments:
// 
//////////////////////////////////////////////////////////////////////////////////


 module ALU_8bit(
    input signed [7:0] a,
    input signed [7:0] b,
    input [4:0] s,

    output reg signed [15:0] result,
    output reg CF,
    output reg ZF,
    output reg OF,
    output reg NF
);

reg [8:0] temp;

always @(*) begin

    result = 16'd0;
    CF = 1'b0;
    OF = 1'b0;

    case(s)

    5'b00000: begin
        temp = {1'b0,a}+{1'b0,b};
        result = a+b;
        CF = temp[8];
        OF = (a[7]==b[7]) && (result[7]!=a[7]);
    end

    5'b00001: begin
        result = a-b;
        CF = (a<b);
        OF = (a[7]!=b[7]) && (result[7]!=a[7]);
    end

    5'b00010: result = a*b;

    5'b00011: begin
        if(b!=0)
            result = a/b;
    end

    5'b00100: begin
        if(b!=0)
            result = a%b;
    end

    5'b00101: result = a & b;
    5'b00110: result = a | b;
    5'b00111: result = a ^ b;
    5'b01000: result = ~(a ^ b);
    5'b01001: result = ~a;
    5'b01010: result = ~(a & b);
    5'b01011: result = ~(a | b);

    5'b01100: result = (a && b);
    5'b01101: result = (a || b);
    5'b01110: result = (!a);

    5'b01111: result = a >> b[2:0];
    5'b10000: result = a << b[2:0];

    5'b10001: result = a >>> b[2:0];
    5'b10010: result = a <<< b[2:0];

    5'b10011: result = {a[0],a[7:1]};
    5'b10100: result = {a[6:0],a[7]};

    5'b10101: result = (a==b);
    5'b10110: result = (a!=b);
    5'b10111: result = (a>b);
    5'b11000: result = (a<b);
    5'b11001: result = (a>=b);
    5'b11010: result = (a<=b);

    default: result = 16'd0;

    endcase

    ZF = (result == 16'd0);
    NF = result[15];

end

endmodule

Project_ALU.srcs/sim_1/new/tb_ALU_8bit.v
`timescale 1ns / 1ps 
//////////////////////////////////////////////////////////////////////////////////
// Company: 
// Engineer: 
// 
// Create Date: 02.06.2026 12:59:46
// Design Name: 
// Module Name: tb_ALU_8bit
// Project Name: 
// Target Devices: 
// Tool Versions: 
// Description: 
// 
// Dependencies: 
// 
// Revision:
// Revision 0.01 - File Created
// Additional Comments:
// 
//////////////////////////////////////////////////////////////////////////////////




module tb_ALU_8bit;

reg signed [7:0] a;
reg signed [7:0] b;
reg [4:0] s;

wire signed [15:0] result;
wire CF;
wire ZF;
wire OF;
wire NF;

ALU_8bit DUT(

    .a(a),
    .b(b),
    .s(s),

    .result(result),
    .CF(CF),
    .ZF(ZF),
    .OF(OF),
    .NF(NF)

);

initial begin

$dumpfile("alu.vcd");
$dumpvars(0,tb_ALU_8bit);

$display("Starting ALU Simulation...");
$monitor("Time=%0t A=%0d B=%0d Opcode=%b Result=%0d CF=%b ZF=%b OF=%b NF=%b",
          $time,a,b,s,result,CF,ZF,OF,NF);


//--------------------------
// ADD
//--------------------------

a = 8'd10;
b = 8'd5;
s = 5'b00000;

#20;


//--------------------------
// SUB
//--------------------------

a = 8'd10;
b = 8'd20;
s = 5'b00001;

#20;


//--------------------------
// MUL
//--------------------------

a = 8'd12;
b = 8'd10;
s = 5'b00010;

#20;


//--------------------------
// DIV
//--------------------------

a = 8'd40;
b = 8'd5;
s = 5'b00011;

#20;


//--------------------------
// DIV BY ZERO
//--------------------------

a = 8'd40;
b = 8'd0;
s = 5'b00011;

#20;


//--------------------------
// MOD
//--------------------------

a = 8'd23;
b = 8'd5;
s = 5'b00100;

#20;


//--------------------------
// AND
//--------------------------

a = 8'b10101010;
b = 8'b11001100;
s = 5'b00101;

#20;


//--------------------------
// OR
//--------------------------

s = 5'b00110;

#20;


//--------------------------
// XOR
//--------------------------

s = 5'b00111;

#20;


//--------------------------
// XNOR
//--------------------------

s = 5'b01000;

#20;


//--------------------------
// NOT
//--------------------------

a = 8'b10101010;
s = 5'b01001;

#20;


//--------------------------
// LEFT SHIFT
//--------------------------

a = 8'd5;
b = 8'd2;
s = 5'b10000;

#20;


//--------------------------
// RIGHT SHIFT
//--------------------------

s = 5'b01111;

#20;


//--------------------------
// ARITHMETIC RIGHT SHIFT
//--------------------------

a = -8'd16;
b = 8'd2;
s = 5'b10001;

#20;


//--------------------------
// ROTATE LEFT
//--------------------------

a = 8'b10010001;
s = 5'b10100;

#20;


//--------------------------
// ROTATE RIGHT
//--------------------------

s = 5'b10011;

#20;


//--------------------------
// EQUAL
//--------------------------

a = 8'd15;
b = 8'd15;
s = 5'b10101;

#20;


//--------------------------
// GREATER THAN
//--------------------------

a = 8'd20;
b = 8'd10;
s = 5'b10111;

#20;


//--------------------------
// LESS THAN
//--------------------------

a = 8'd5;
b = 8'd10;
s = 5'b11000;

#20;


//--------------------------
// OVERFLOW TEST
//--------------------------

a = 8'd127;
b = 8'd1;
s = 5'b00000;

#20;


//--------------------------
// NEGATIVE RESULT TEST
//--------------------------

a = 8'd5;
b = 8'd10;
s = 5'b00001;

#20;


$display("Simulation Complete");

$finish;

end

endmodule

Project_ALU.sim/sim_1/behav/xsim/alu.vcd
$date
   Tue Jun  2 14:15:51 2026
$end

$version
  2025.2
  $dumpfile ("alu.vcd") 
$end

$timescale
  1ps
$end

$scope module tb_ALU_8bit $end
$var reg 8 ! a [7:0] $end
$var reg 8 " b [7:0] $end
$var reg 5 # s [4:0] $end
$var wire 16 $ result [15:0] $end
$var wire 1 % CF $end
$var wire 1 & ZF $end
$var wire 1 ' OF $end
$var wire 1 ( NF $end
$scope module DUT $end
$var wire 8 ) a [7:0] $end
$var wire 8 * b [7:0] $end
$var wire 5 + s [4:0] $end
$var reg 16 , result [15:0] $end
$var reg 1 - CF $end
$var reg 1 . ZF $end
$var reg 1 / OF $end
$var reg 1 0 NF $end
$var reg 9 1 temp [8:0] $end
$upscope $end
$upscope $end
$enddefinitions $end

#0
$dumpvars
b1010 !
b101 "
b0 #
b1111 $
0%
0&
0'
0(
b1010 )
b101 *
b0 +
b1111 ,
0-
0.
0/
00
b1111 1
$end

#20000
b10100 "
b1 #
b1111111111110110 $
1%
1(
b10100 *
b1 +
b1111111111110110 ,
1-
10

#40000
b1100 !
b1010 "
b10 #
b1111000 $
0%
0(
b1100 )
b1010 *
b10 +
b1111000 ,
0-
00

#60000
b101000 !
b101 "
b11 #
b1000 $
b101000 )
b101 *
b11 +
b1000 ,

#80000
b0 "
b0 $
1&
b0 *
b0 ,
1.

#100000
b10111 !
b101 "
b100 #
b11 $
0&
b10111 )
b101 *
b100 +
b11 ,
0.

#120000
b10101010 !
b11001100 "
b101 #
b1111111110001000 $
1(
b10101010 )
b11001100 *
b101 +
b1111111110001000 ,
10

#140000
b110 #
b1111111111101110 $
b110 +
b1111111111101110 ,

#160000
b111 #
b1100110 $
0(
b111 +
b1100110 ,
00

#180000
b1000 #
b1111111110011001 $
1(
b1000 +
b1111111110011001 ,
10

#200000
b1001 #
b1010101 $
0(
b1001 +
b1010101 ,
00

#220000
b101 !
b10 "
b10000 #
b10100 $
b101 )
b10 *
b10000 +
b10100 ,

#240000
b1111 #
b1 $
b1111 +
b1 ,

#260000
b11110000 !
b10001 #
b1111111111111100 $
1(
b11110000 )
b10001 +
b1111111111111100 ,
10

#280000
b10010001 !
b10100 #
b100011 $
0(
b10010001 )
b10100 +
b100011 ,
00

#300000
b10011 #
b11001000 $
b10011 +
b11001000 ,

#320000
b1111 !
b1111 "
b10101 #
b1 $
b1111 )
b1111 *
b10101 +
b1 ,

#340000
b10100 !
b1010 "
b10111 #
b10100 )
b1010 *
b10111 +
b1 ,

#360000
b101 !
b11000 #
b101 )
b11000 +
b1 ,

#380000
b1111111 !
b1 "
b0 #
b10000000 $
1'
b1111111 )
b1 *
b0 +
b10000000 ,
1/
b10000000 1

#400000
b101 !
b1010 "
b1 #
b1111111111111011 $
1%
0'
1(
b101 )
b1010 *
b1 +
b1111111111111011 ,
1-
0/
10
